pcap_ioc/__init__.py
pcap_ioc/cli.py
pcap_ioc/pcap.py
pcap_ioc-0.1.2.dist-info/LICENSE
pcap_ioc-0.1.2.dist-info/METADATA
pcap_ioc-0.1.2.dist-info/WHEEL
pcap_ioc-0.1.2.dist-info/entry_points.txt
pcap_ioc-0.1.2.dist-info/top_level.txt
pcap_ioc-0.1.2.dist-info/RECORD
