Metadata-Version: 2.1
Name: pcap-ioc
Version: 0.1.2
Summary: Python library extracting potential IOCs from a pcap file
Home-page: https://github.com/Nothing2Hide/pcapanalysis
Author: Tek
Author-email: tek@randhome.io
License: MIT
Keywords: threat-intel
Platform: UNKNOWN
Classifier: Programming Language :: Python :: 3
Classifier: License :: OSI Approved :: MIT License
Classifier: Operating System :: OS Independent
Requires-Dist: pyshark (==0.4.2.2)
Requires-Dist: IPy (==0.83)
Requires-Dist: pymisp (==2.4.101)
